harriet/__init__.py
harriet/core.py
harriet/urls.py
harriet-0.1.0.dist-info/LICENSE.md
harriet-0.1.0.dist-info/WHEEL
harriet-0.1.0.dist-info/METADATA
harriet-0.1.0.dist-info/RECORD
